myfilesize/__init__.py
myfilesize/find_files.py
myfilesize-1.0.0.dist-info/LICENSE
myfilesize-1.0.0.dist-info/METADATA
myfilesize-1.0.0.dist-info/WHEEL
myfilesize-1.0.0.dist-info/top_level.txt
myfilesize-1.0.0.dist-info/RECORD
