Metadata-Version: 2.1
Name: myfilesize
Version: 1.0.0
Summary: A package to find small and large files in a directory
Home-page: https://github.com/Bytebreach/myfilesize
Author: MrFidal
Author-email: mrfidal@proton.me
Classifier: Programming Language :: Python :: 3
Classifier: License :: OSI Approved :: MIT License
Classifier: Operating System :: OS Independent
Requires-Python: >=3.6
License-File: LICENSE
